MANIFEST.in
README.rst
setup.cfg
setup.py
xapian/bindings.py
xapian_bindings.egg-info/PKG-INFO
xapian_bindings.egg-info/SOURCES.txt
xapian_bindings.egg-info/dependency_links.txt
xapian_bindings.egg-info/not-zip-safe
xapian_bindings.egg-info/top_level.txt