Metadata-Version: 2.1
Name: xapian-bindings
Version: 0.1.0
Summary: Meta-package to build and install xapian-bindings extension.
Home-page: https://github.com/ninemoreminutes/xapian-bindings/
Author: Chris Church
Author-email: chris@ninemoreminutes.com
License: BSD
Project-URL: Documentation, https://github.com/ninemoreminutes/xapian-bindings/
Project-URL: Source, https://github.com/ninemoreminutes/xapian-bindings/
Project-URL: Tracker, https://github.com/ninemoreminutes/xapian-bindings/issues
Keywords: xapian,bindings,haystack
Platform: UNKNOWN
Classifier: Development Status :: 3 - Alpha
Classifier: Intended Audience :: Developers
Classifier: License :: OSI Approved :: BSD License
Classifier: Operating System :: OS Independent
Classifier: Programming Language :: Python
Classifier: Programming Language :: Python :: 3
Classifier: Programming Language :: Python :: 3.4
Classifier: Programming Language :: Python :: 3.5
Classifier: Programming Language :: Python :: 3.6
Classifier: Programming Language :: Python :: 3.7
Classifier: Programming Language :: Python :: 3.8
Classifier: Topic :: Software Development :: Libraries
Classifier: Topic :: Software Development :: Libraries :: Python Modules
